fse/__init__.py
fse/inputs.py
fse/vectors.py
fse/models/__init__.py
fse/models/average.py
fse/models/average_inner.c
fse/models/average_inner.cpython-38-darwin.so
fse/models/average_inner.pxd
fse/models/average_inner.pyx
fse/models/base_s2v.py
fse/models/sentencevectors.py
fse/models/sif.py
fse/models/usif.py
fse/models/utils.py
fse/models/voidptr.h
test/__init__.py
test/test_average.py
test/test_base_s2v.py
test/test_inputs.py
test/test_sentencevectors.py
test/test_sif.py
test/test_usif.py
test/test_utils.py
test/test_vectors.py
fse-1.0.0.dist-info/LICENSE
fse-1.0.0.dist-info/METADATA
fse-1.0.0.dist-info/WHEEL
fse-1.0.0.dist-info/top_level.txt
fse-1.0.0.dist-info/RECORD
